headecpt/__init__.py
headecpt/basic_struct.py
headecpt/encrypt_funcs.py
headecpt/head_struct.py
headecpt/main.py
headecpt/rws/__init__.py
headecpt/rws/rw.py
headecpt-0.1.3.dist-info/LICENSE
headecpt-0.1.3.dist-info/METADATA
headecpt-0.1.3.dist-info/WHEEL
headecpt-0.1.3.dist-info/entry_points.txt
headecpt-0.1.3.dist-info/top_level.txt
headecpt-0.1.3.dist-info/RECORD
