Metadata-Version: 2.1
Name: headecpt
Version: 0.1.3
Summary: encrypt/decrypt file header for simple and quick encrypt/decrypt
Home-page: https://github.com/lichunown/head-encrypt.git
Author: lcy
Author-email: lichunyang_1@outlook.com
Classifier: Programming Language :: Python :: 3
Classifier: Programming Language :: Python :: 3.7
Classifier: Programming Language :: Python :: 3.8
Classifier: Programming Language :: Python :: 3.9
Classifier: Programming Language :: Python :: 3.10
Classifier: Programming Language :: Python :: 3.11
Classifier: Programming Language :: Python :: 3.12
Classifier: License :: OSI Approved :: MIT License
Classifier: Operating System :: OS Independent
Classifier: Natural Language :: Chinese (Simplified)
Classifier: Topic :: File Formats
Requires-Python: >=3.6
License-File: LICENSE
Requires-Dist: click
Provides-Extra: crypto
Requires-Dist: pycryptodome; extra == "crypto"
